genomes_attributes_viewer/__init__.py
genomes_attributes_viewer/app.py
genomes_attributes_viewer/first_run.py
genomes_attributes_viewer/prepare_attributes.py
genomes_attributes_viewer/prepare_names.py
genomes_attributes_viewer/data/accession_taxid_attribute.tsv.gz
genomes_attributes_viewer-1.3.data/scripts/genomes-attributes-viewer
genomes_attributes_viewer-1.3.dist-info/AUTHORS.txt
genomes_attributes_viewer-1.3.dist-info/METADATA
genomes_attributes_viewer-1.3.dist-info/WHEEL
genomes_attributes_viewer-1.3.dist-info/top_level.txt
genomes_attributes_viewer-1.3.dist-info/RECORD
