Metadata-Version: 2.1
Name: genomes-attributes-viewer
Version: 1.3
Summary: Example application of fastsubtrees
Home-page: https://github.com/ggonnella/fastsubtrees/"+            "tree/main/genomes_attributes_viewer
Author: Giorgio Gonnella
Author-email: gonnella@zbh.uni-hamburg.de
License: ISC
Keywords: ncbi taxonomy webapp dash fastsubtrees
Platform: UNKNOWN
Classifier: Development Status :: 5 - Production/Stable
Classifier: Environment :: Console
Classifier: Intended Audience :: Developers
Classifier: Intended Audience :: End Users/Desktop
Classifier: Intended Audience :: Science/Research
Classifier: License :: OSI Approved :: ISC License (ISCL)
Classifier: Operating System :: MacOS :: MacOS X
Classifier: Operating System :: POSIX :: Linux
Classifier: Programming Language :: Python :: 3 :: Only
Classifier: Topic :: Software Development :: Libraries
License-File: AUTHORS.txt
Requires-Dist: fastsubtrees (>=2.0)
Requires-Dist: ntdownload
Requires-Dist: dash (==2.0.0)
Requires-Dist: dash-bootstrap-components (==1.0.2)
Requires-Dist: dash-core-components (==2.0.0)
Requires-Dist: dash-html-components (==2.0.0)
Requires-Dist: dash-table (==5.0.0)
Requires-Dist: Werkzeug (==2.0.0)
Requires-Dist: Flask (==2.1.2)
Requires-Dist: pandas
